<?xml version="1.0" encoding="utf-8" ?>
<dwsync>
<file name="06view_cad.asp" server="S:/myindaia/" local="128058212260000000" remote="128058212260000000" />
<file name="06view_edt.asp" server="S:/myindaia/" local="128058212260000000" remote="128058212260000000" />
<file name="06view_lst.asp" server="S:/myindaia/" local="128058212240000000" remote="128058212240000000" />
<file name="06view_nav.asp" server="S:/myindaia/" local="128058212260000000" remote="128058212260000000" />
<file name="07view_campo_lst.asp" server="S:/myindaia/" local="128058212260000000" remote="128058212260000000" />
<file name="08view_filtro_lst.asp" server="S:/myindaia/" local="128058212260000000" remote="128058212260000000" />
<file name="permissao.asp" server="S:/myindaia/" local="128152391900000000" remote="128152391900000000" />
<file name="permissao_edt.asp" server="S:/myindaia/" local="128157694280000000" remote="128157694280000000" />
<file name="personal.asp" server="S:/myindaia/" local="128157802020000000" remote="128157802020000000" />
<file name="personal_edt.asp" server="S:/myindaia/" local="128157810840000000" remote="128157810840000000" />
<file name="personal_filtro.asp" server="S:/myindaia/" local="128190708140000000" remote="128190708140000000" />
</dwsync>